tool_llama/.DS_Store
tool_llama/__init__.py
tool_llama/use_tool.py
tool_llama/utils/__init__.py
tool_llama/utils/_pydantic.py
tool_llama/utils/basemodel_utils.py
tool_llama/utils/function_utils.py
tool_llama-0.0.7.dist-info/METADATA
tool_llama-0.0.7.dist-info/WHEEL
tool_llama-0.0.7.dist-info/licenses/LICENSE
tool_llama-0.0.7.dist-info/RECORD
