Metadata-Version: 2.1
Name: tool_llama
Version: 0.0.7
Summary: Open source library of large model usage tools.(开源大模型使用工具的库.)
Project-URL: Homepage, https://github.com/limoncc/tool_llama
Project-URL: Bug Tracker, https://github.com/limoncc/tool_llama/issues
Author-email: limoncc <limoncc@icloud.com>
License-File: LICENSE
Classifier: License :: OSI Approved :: MIT License
Classifier: Operating System :: OS Independent
Classifier: Programming Language :: Python :: 3
Requires-Python: >=3
Requires-Dist: llama-cpp-python
Requires-Dist: openai>=1.3.5
Requires-Dist: pydantic>=2.4.2
Requires-Dist: rtoml>=0.9.0
Requires-Dist: typing-extensions
